AUTHORS
MANIFEST.in
README.creole
setup.py
django_sync_server.egg-info/PKG-INFO
django_sync_server.egg-info/SOURCES.txt
django_sync_server.egg-info/dependency_links.txt
django_sync_server.egg-info/not-zip-safe
django_sync_server.egg-info/requires.txt
django_sync_server.egg-info/top_level.txt
testproject/__init__.py
testproject/logger.conf
testproject/manage.py
testproject/settings.py
testproject/urls.py
testproject/views.py
testproject/weave_server.py
testproject/weave_server_tester.py
testproject/templates/testproject/url_info.html
weave/__init__.py
weave/admin.py
weave/app_settings.py
weave/constants.py
weave/decorators.py
weave/models.py
weave/tests.py
weave/urls.py
weave/utils.py
weave/migrations/0001_initial.py
weave/migrations/0002_add_field_wbo_ttl.py
weave/migrations/0003_add_field_payload_size.py
weave/migrations/__init__.py
weave/views/__init__.py
weave/views/misc.py
weave/views/sync.py
weave/views/user.py