Metadata-Version: 1.1
Name: django-sync-server
Version: 0.4.2
Summary: django-sync-server is a Django reusable application witch implements a Firefox weave server.
Home-page: http://code.google.com/p/django-sync-server/
Author: Jens Diemer
Author-email: django-sync-server@jensdiemer.de
License: UNKNOWN
Platform: UNKNOWN
Classifier: Development Status :: 5 - Production/Stable
Classifier: Environment :: Web Environment
Classifier: Intended Audience :: Developers
Classifier: License :: OSI Approved :: GNU General Public License (GPL)
Classifier: Programming Language :: Python
Classifier: Framework :: Django
Classifier: Topic :: Database :: Front-Ends
Classifier: Topic :: Documentation
Classifier: Topic :: Internet :: WWW/HTTP :: Dynamic Content
Classifier: Topic :: Internet :: WWW/HTTP :: WSGI :: Application
Classifier: Operating System :: OS Independent
